kerndeterminer-0.0.1.dist-info/METADATA
kerndeterminer-0.0.1.dist-info/WHEEL
kerndeterminer/__init__.py
kerndeterminer/kerndeterminer.cpython-39-darwin.so
kerndeterminer-0.0.1.dist-info/RECORD
