Metadata-Version: 2.1
Name: kerndeterminer
Version: 0.0.1
Summary: Work out how far apart things should be (very quickly)
Author: Simon Cozens <simon@simon-cozens.org>
Author-email: Simon Cozens <simon@simon-cozens.org>
Project-URL: Source Code, https://github.com/simoncozens/kerndeterminer
